py_surepetcare-0.5.10.dist-info/licenses/LICENSE
surepccli/__init__.py
surepccli/account.py
surepccli/const.py
surepccli/device.py
surepccli/helpers.py
surepccli/pet.py
surepccli/session.py
surepccli/typer.py
surepccli/devices/__init__.py
surepccli/devices/dual_scan_connect.py
surepccli/devices/dual_scan_pet_door.py
surepccli/devices/feeder_connect.py
surepccli/devices/helper.py
surepccli/devices/hub.py
surepccli/devices/pet_door.py
surepcio/__init__.py
surepcio/client.py
surepcio/command.py
surepcio/const.py
surepcio/enums.py
surepcio/household.py
surepcio/devices/__init__.py
surepcio/devices/device.py
surepcio/devices/dual_scan_connect.py
surepcio/devices/dual_scan_pet_door.py
surepcio/devices/entities.py
surepcio/devices/feeder_connect.py
surepcio/devices/hub.py
surepcio/devices/no_id_dog_bowl_connect.py
surepcio/devices/pet.py
surepcio/devices/pet_door.py
surepcio/devices/poseidon_connect.py
surepcio/entities/__init__.py
surepcio/entities/battery_mixin.py
surepcio/entities/error_mixin.py
surepcio/security/auth.py
surepcio/security/cache.py
surepcio/security/exceptions.py
surepcio/security/redact.py
py_surepetcare-0.5.10.dist-info/METADATA
py_surepetcare-0.5.10.dist-info/WHEEL
py_surepetcare-0.5.10.dist-info/entry_points.txt
py_surepetcare-0.5.10.dist-info/top_level.txt
py_surepetcare-0.5.10.dist-info/RECORD
