Metadata-Version: 2.4
Name: py-surepetcare
Version: 0.5.10
Summary: Python library for SurePetcare API
Author: FredrikM97
License: MIT
Classifier: Intended Audience :: Developers
Classifier: Topic :: Home Automation
Classifier: Topic :: Software Development :: Libraries :: Python Modules
Classifier: Programming Language :: Python :: 3
Classifier: Programming Language :: Python :: 3.13
Classifier: License :: OSI Approved :: MIT License
Classifier: Operating System :: OS Independent
Requires-Python: >=3.13
License-File: LICENSE
Requires-Dist: aiohttp>=3.9.0
Requires-Dist: pydantic>=2.11.7
Provides-Extra: dev
Requires-Dist: aresponses; extra == "dev"
Requires-Dist: pytest>=8.3.5; extra == "dev"
Requires-Dist: pytest-asyncio>=0.26.0; extra == "dev"
Requires-Dist: python-dotenv>=1.1.0; extra == "dev"
Requires-Dist: pre_commit>=4.2.0; extra == "dev"
Requires-Dist: pytest-cov>=4.1.0; extra == "dev"
Requires-Dist: syrupy; extra == "dev"
Requires-Dist: nest_asyncio; extra == "dev"
Provides-Extra: cli
Requires-Dist: typer>=0.19.2; extra == "cli"
Requires-Dist: rich==14.2.0; extra == "cli"
Requires-Dist: python-dotenv>=1.1.0; extra == "cli"
Dynamic: license-file
